ebest/OpenApi.py
ebest/__init__.py
ebest/code_realtime_account.py
ebest/tr_code_to_path.py
ebest-1.0.2.dist-info/METADATA
ebest-1.0.2.dist-info/WHEEL
ebest-1.0.2.dist-info/licenses/LICENSE
ebest-1.0.2.dist-info/RECORD
