Metadata-Version: 2.3
Name: ebest
Version: 1.0.2
Summary: package for ebest api
Project-URL: Homepage, https://github.com/teranum/python-packages/tree/master/ebest
Author-email: teranum <teranum@gmail.com>
Classifier: License :: OSI Approved :: MIT License
Classifier: Operating System :: OS Independent
Classifier: Programming Language :: Python :: 3
Requires-Python: >=3.8
Requires-Dist: aiohttp
